kernel_install/__init__.py
kernel_install/cli.py
kernel_install/install.py
kernel_install/logger.py
kernel_install/py.typed
kernel_install/tests/__init__.py
kernel_install/tests/conftest.py
kernel_install/tests/test_kernel_cli.py
kernel_install/tests/test_kernel_creation.py
kernel_install-2404.0.1.dist-info/entry_points.txt
kernel_install-2404.0.1.dist-info/LICENSE
kernel_install-2404.0.1.dist-info/WHEEL
kernel_install-2404.0.1.dist-info/METADATA
kernel_install-2404.0.1.dist-info/RECORD
