Metadata-Version: 2.1
Name: kernel-install
Version: 2404.0.1
Summary: Utility to install various jupyter kernel specs.
Author-email: "DKRZ, Clint" <freva@dkrz.de>
Requires-Python: >=3.8
Classifier: Development Status :: 4 - Beta
Classifier: Environment :: Console
Classifier: Intended Audience :: Developers
Classifier: Intended Audience :: Science/Research
Classifier: License :: OSI Approved :: BSD License
Classifier: Operating System :: POSIX :: Linux
Classifier: Programming Language :: Python :: 3
Requires-Dist: appdirs
Requires-Dist: bash_kernel
Requires-Dist: ipykernel
Requires-Dist: rich
Requires-Dist: rich-argparse
Requires-Dist: tox ; extra == "dev"
Requires-Dist: flit ; extra == "dev"
Requires-Dist: pytest ; extra == "dev"
Requires-Dist: pytest-cov ; extra == "dev"
Requires-Dist: pytest-mock ; extra == "dev"
Requires-Dist: mock ; extra == "dev"
Requires-Dist: pytest-env ; extra == "dev"
Project-URL: Documentation, https://github.com/FREVA-CLINT/install-kernelspec/README.md
Project-URL: Home, https://github.com/FREVA-CLINT/install-kernelspec
Project-URL: Issues, https://github.com/FREVA-CLINT/install-kernelspec/issues
Project-URL: Source, https://github.com/FREVA-CLINT/install-kernelspec
Provides-Extra: dev
